ftsf/__init__.py
ftsf/backtest.py
ftsf/evaluation.py
ftsf/model.py
ftsf/preprocessing.py
ftsf/scaler.py
ftsf/utils.py
ftsf/tests/test_evaluation.py
ftsf/tests/test_preprocessing.py
ftsf/tests/test_scaler.py
ftsf-0.0.2.3.dist-info/LICENSE
ftsf-0.0.2.3.dist-info/METADATA
ftsf-0.0.2.3.dist-info/WHEEL
ftsf-0.0.2.3.dist-info/top_level.txt
ftsf-0.0.2.3.dist-info/RECORD
