Metadata-Version: 2.1
Name: ftsf
Version: 0.0.2.3
Summary: Package for financial time series forecasting.
Author-email: Nikita Safonov <sixxio@yandex.ru>
Project-URL: Homepage, https://github.com/sixxio/ftsf
Project-URL: Documentation, https://sixxio.github.io/ftsf/
Project-URL: Bug Tracker, https://github.com/sixxio/ftsf/issues
Classifier: Development Status :: 3 - Alpha
Classifier: Programming Language :: Python :: 3
Classifier: License :: OSI Approved :: MIT License
Classifier: Operating System :: OS Independent
Requires-Python: >=3.7
License-File: LICENSE
Requires-Dist: numpy
Requires-Dist: pandas
Requires-Dist: scikit-learn
Requires-Dist: statsmodels
Requires-Dist: catboost
Requires-Dist: xgboost
Requires-Dist: tensorflow
